knime.py
knime-0.11.6.dist-info/LICENSE
knime-0.11.6.dist-info/METADATA
knime-0.11.6.dist-info/WHEEL
knime-0.11.6.dist-info/top_level.txt
knime-0.11.6.dist-info/RECORD
