Metadata-Version: 2.1
Name: knime
Version: 0.11.6
Summary: Tools for reading and executing KNIME workflows.
Home-page: https://www.knime.com/
Author: Appliomics, LLC
Author-email: davin+knimepy@appliomics.com
License: GPLv3
Project-URL: Source, https://github.com/KNIME/knimepy
Platform: any
Classifier: Development Status :: 4 - Beta
Classifier: Intended Audience :: Developers
Classifier: Intended Audience :: End Users/Desktop
Classifier: Programming Language :: Python :: 3.6
Classifier: Programming Language :: Python :: 3.7
Classifier: Programming Language :: Python :: 3.8
Classifier: Programming Language :: Python :: 3.9
Classifier: License :: OSI Approved :: GNU General Public License v3 (GPLv3)
